teleglog/__init__.py
teleglog/teleglog.py
teleglog-0.1.2.dist-info/LICENSE
teleglog-0.1.2.dist-info/METADATA
teleglog-0.1.2.dist-info/WHEEL
teleglog-0.1.2.dist-info/top_level.txt
teleglog-0.1.2.dist-info/RECORD
